{"version":2,"baseVals":{"rating":5,"gammaadj":1,"decay":0.925,"echo_zoom":1.002,"wave_mode":5,"wave_thick":1,"modwavealphabyvolume":1,"wave_brighten":0,"darken":1,"wave_a":1.136,"wave_scale":1.951,"wave_smoothing":0.9,"wave_mystery":0.094,"modwavealphastart":1.14,"modwavealphaend":1.3,"warpanimspeed":1.459,"warpscale":2.007,"zoom":0.9999,"warp":0.01,"sx":0.9999,"wave_g":0.83,"wave_b":1.24,"wave_x":0.86,"ob_size":0,"ob_a":1,"ib_size":0.26,"mv_b":1.2,"mv_a":0},"shapes":[{"baseVals":{},"init_eqs_str":" ","frame_eqs_str":"","init_eqs_eel":"","frame_eqs_eel":""},{"baseVals":{},"init_eqs_str":" ","frame_eqs_str":"","init_eqs_eel":"","frame_eqs_eel":""},{"baseVals":{},"init_eqs_str":" ","frame_eqs_str":"","init_eqs_eel":"","frame_eqs_eel":""},{"baseVals":{},"init_eqs_str":" ","frame_eqs_str":"","init_eqs_eel":"","frame_eqs_eel":""}],"waves":[{"baseVals":{},"init_eqs_str":" ","frame_eqs_str":"","point_eqs_str":"","init_eqs_eel":"","frame_eqs_eel":"","point_eqs_eel":""},{"baseVals":{},"init_eqs_str":" ","frame_eqs_str":"","point_eqs_str":"","init_eqs_eel":"","frame_eqs_eel":"","point_eqs_eel":""},{"baseVals":{},"init_eqs_str":" ","frame_eqs_str":"","point_eqs_str":"","init_eqs_eel":"","frame_eqs_eel":"","point_eqs_eel":""},{"baseVals":{},"init_eqs_str":" ","frame_eqs_str":"","point_eqs_str":"","init_eqs_eel":"","frame_eqs_eel":"","point_eqs_eel":""}],"init_eqs_str":"(function(){a['n'] = 0; a['reg70'] = 0; a['in1a'] = 0; a['ou2a'] = 0; a['s'] = 0; a['tcos'] = 0; a['reg05'] = 0; a['b2a0'] = 0; a['q21'] = 0; a['q15'] = 0; a['dt'] = 0; a['q'] = 0; a['bt'] = 0; a['q1'] = 0; a['r1'] = 0; a['q5'] = 0; a['r5'] = 0; a['q9'] = 0; a['v_'] = 0; a['dec_s'] = 0; a['b0a0'] = 0; a['a2a0'] = 0; a['in2b'] = 0; a['lob'] = 0; a['omega'] = 0; a['bpm'] = 0; a['q24'] = 0; a['q11'] = 0; a['pi'] = 0; a['q10'] = 0; a['reg06'] = 0; a['dec_m'] = 0; a['q4'] = 0; a['gri'] = 0; a['r2'] = 0; a['loa'] = 0; a['c2'] = 0; a['dir'] = 0; a['reg71'] = 0; a['ou1a'] = 0; a['xb'] = 0; a['ang'] = 0; a['r2_'] = 0; a['ou2b'] = 0; a['c3'] = 0; a['fg'] = 0; a['a1a0'] = 0; a['a1'] = 0; a['b2'] = 0; a['vol'] = 0; a['alpha'] = 0; a['idx2'] = 0; a['reg32'] = 0; a['a0'] = 0; a['r1_'] = 0; a['c4'] = 0; a['q2'] = 0; a['idx'] = 0; a['b1a0'] = 0; a['q3'] = 0; a['b0'] = 0; a['t0'] = 0; a['vol_'] = 0; a['dec'] = 0; a['xa'] = 0; a['c5'] = 0; a['ou1b'] = 0; a['bt_'] = 0; a['in2a'] = 0; a['c6'] = 0; a['a2'] = 0; a['pk'] = 0; a['c1'] = 0; a['in1b'] = 0; a['b1'] = 0; a['reg60'] = 0; a['n']=-10000; for(var mdparser_idx688=0;mdparser_idx688<20000;mdparser_idx688++){a['megabuf'][Math.floor(a['n'])]=0; a['gmegabuf'][Math.floor(a['n'])]=0; a['n']+=1;} a['minbpm']=35; a['maxbpm']=210; a['num_res']=400; a['index']=0; for(var mdparser_idx689=0;mdparser_idx689<a['num_res'];mdparser_idx689++){a['n']=(a['index']*8); a['bpm']=(a['minbpm']*pow(div(a['maxbpm'],a['minbpm']), div(a['index'],(a['num_res']-1)))); a['megabuf'][Math.floor(a['n'])]=a['bpm']; a['index']+=1;} a['reg05']=2; a['pi']=3.1416; a['reg71']=16000;}());","frame_eqs_str":"(function(){a['bpm']=135; a['dt']=Math.min(div(1,a['fps']), 0.1); a['dec_m']=(1-(4*a['dt'])); a['dec_s']=(1-a['dt']); a['vol']=div(((a['bass']+a['mid'])+a['treb']),3); a['vol_']=((a['vol_']*a['dec_m'])+((1-a['dec_m'])*a['vol'])); a['bt']=((((a['vol']>a['pk'])?1:0)&&((a['time']>(a['t0']+1))?1:0))?1:0); ((Math.abs(a['bt'])>0.00001)?((function(){a['t0']=a['time']; a['pk']=(4+(a['vol']*4)); return a['reg70']=0;})()):(0)); a['pk']-=(a['dt']*pow(div(a['reg70'],a['reg71']), 2)); a['idx']+=a['bt']; a['idx2']+=(a['bt']*((Math.abs((mod(a['idx'],4))-(0))<0.00001)?1:0)); a['q21']=(Math.max(0.3, Math.min(1.7, (a['vol_']-0.2)))*0.8); a['q24']=a['bt']; a['n']=49; for(var mdparser_idx690=0;mdparser_idx690<50;mdparser_idx690++){a['megabuf'][Math.floor((a['n']+1))]=a['megabuf'][Math.floor(a['n'])]; a['n']-=1;} a['megabuf'][Math.floor(0)]=a['bt']; ((Math.abs(a['bt'])>0.00001)?((function(){a['r1']=rand(1); return a['r2']=rand(0);})()):(0)); a['r1_']=((a['r1_']*0.95)+(0.05*a['r1'])); a['r2_']=((a['r2_']*0.9)+(0.1*a['r2'])); a['fg']=div(div(a['bpm'],60),2); a['q']=5; a['omega']=(6.283*Math.min(0.5, div(a['fg'],a['fps']))); a['tcos']=Math.cos(a['omega']); a['alpha']=div(Math.sin(a['omega']),(2*a['q'])); a['b0']=div((1-a['tcos']),2); a['b1']=(1-a['tcos']); a['b2']=div((1-a['tcos']),2); a['a0']=(1+a['alpha']); a['a1']=(-2*a['tcos']); a['a2']=(1-a['alpha']); a['b0a0']=div(a['b0'],a['a0']); a['b1a0']=div(a['b1'],a['a0']); a['b2a0']=div(a['b2'],a['a0']); a['a1a0']=div(a['a1'],a['a0']); a['a2a0']=div(a['a2'],a['a0']); a['xa']=a['r1_']; a['loa']=(((((a['b0a0']*a['xa'])+(a['b1a0']*a['in1a']))+(a['b2a0']*a['in2a']))-(a['a1a0']*a['ou1a']))-(a['a2a0']*a['ou2a'])); a['in2a']=a['in1a']; a['in1a']=a['xa']; a['ou2a']=a['ou1a']; a['ou1a']=a['loa']; a['xa']=a['loa']; a['xb']=a['r2_']; a['lob']=(((((a['b0a0']*a['xb'])+(a['b1a0']*a['in1b']))+(a['b2a0']*a['in2b']))-(a['a1a0']*a['ou1b']))-(a['a2a0']*a['ou2b'])); a['in2b']=a['in1b']; a['in1b']=a['xb']; a['ou2b']=a['ou1b']; a['ou1b']=a['lob']; a['xb']=a['lob']; a['q10']=a['xa']; a['q11']=a['xb']; ((Math.abs(a['bt_'])>0.00001)?((function(){a['c1']=Math.floor((1+rand(9))); a['c2']=Math.floor((1+rand(9))); a['c3']=Math.floor((1+rand(9))); return a['r5']=rand(1);})()):(0)); a['q1']=Math.floor((((a['c1']*100)+(a['c2']*10))+a['c3'])); ((Math.abs(a['bt_'])>0.00001)?((function(){a['c4']=(1+rand(9)); a['c5']=(1+rand(9)); return a['c6']=(1+rand(9));})()):(0)); a['s']=div(9,Math.max(a['c4'], Math.max(a['c5'], a['c6']))); a['q4']=((Math.floor(((a['c4']*a['s'])*100))+Math.floor(((a['c5']*a['s'])*10)))+Math.floor((a['s']*a['c6']))); a['q2']=((a['r5']*0.9)+0.1); a['bt_']=a['bt']; ((Math.abs(a['bt'])>0.00001)?((function(){a['reg05']=(2+Math.floor(rand(4))); a['dir']=((Math.abs(((rand(1)>0.5)?1:0))>0.00001)?(1):(-1)); return a['gri']=(3+(rand(4)*rand(4)));})()):(0)); a['ang']+=(((div(a['bpm'],60)*4)*a['dir'])*a['dt']); a['q5']=a['gri']; a['reg60']=div(30,a['fps']); a['reg06']=(0.04*a['aspecty']); a['reg32']=a['aspecty']; a['q9']=div((a['ang']*a['pi']),4); a['dec']=((Math.abs(((a['vol']>a['v_'])?1:0))>0.00001)?(0.5):(a['dec_m'])); a['v_']=((a['dec']*a['v_'])+((1-a['dec'])*a['vol'])); a['q15']=(sqrt(a['v_'])*0.8); a['q3']=4;}());","pixel_eqs_str":"(function(){a['rot']=0; a['warp']=0; a['dy']=-0.00; a['dx']=-1; a['zoom']=1; a['rot']=(div((3.1416*2),3)*0);}());","init_eqs_eel":"n = -10000; loop (20000, megabuf(n)=0; gmegabuf(n)=0; n +=1; );\n\nMINBPM = 35; MAXBPM = 210; num_res = 400; \nindex = 0;\nloop (num_res,\n  n = index*8;\n  BPM      = minbpm * pow(maxbpm/minbpm,index/(num_res-1));\n  megabuf(n) = BPM;\n  index += 1;\n);\n\nreg05 = 2; //num_c\npi = 3.1416;\nreg71=16000; //glb lim","frame_eqs_eel":"BPM=135;\ndt = min (1/fps,0.1) ;\ndec_m = 1-4*dt; dec_s = 1-dt;\nvol =  (bass+mid+treb)/3; \nvol_ = vol_*dec_m + (1-dec_m)*vol; \nbt=(vol>pk)&&(time>t0+1);\nif(bt,t0=time;pk=4+vol*4;reg70=0,0);\npk-=dt*pow(reg70/reg71,2); idx+=bt; idx2+=bt*(idx%4==0);\n\nq21 = max(0.3,min(1.7,vol_-0.2))*0.8;\nq24 = bt;\n\nn=49; loop(50,megabuf(n+1)=megabuf(n); n-=1); megabuf(0)=bt;\n\nif(bt,r1=rand(1);r2=rand(0),0);\n//if(megabuf(6)==1,r2=rand(1),0);\nr1_=r1_*0.95+0.05*r1;\nr2_=r2_*0.9+0.1*r2;\n\nfg = BPM/60/2; Q=5; omega = 6.283*min(0.5,fg/fps); tcos = cos (omega); alpha = sin(omega)/(2*Q);\nb0=(1-tcos)/2; b1=1-tcos; b2=(1-tcos)/2; a0=1+alpha; a1=-2*tcos; a2=1-alpha;\nb0a0=b0/a0; b1a0=b1/a0; b2a0=b2/a0; a1a0=a1/a0; a2a0=a2/a0;\n\nXa = r1_; LOa= b0a0*Xa + b1a0*in1a + b2a0*in2a - a1a0*ou1a - a2a0*ou2a;\nin2a =in1a; in1a =Xa; ou2a =ou1a;  ou1a =LOa; Xa =LOa;\n\nXb = r2_; LOb= b0a0*Xb + b1a0*in1b + b2a0*in2b - a1a0*ou1b - a2a0*ou2b;\nin2b =in1b; in1b =Xb; ou2b =ou1b;  ou1b =LOb; Xb =LOb;\n\nq10 =xa;\nq11 =xb;\n\nif (bt_,c1=int(1+rand(9));c2=int(1+rand(9));c3=int(1+rand(9));r5=rand(1),0);\nq1=int(c1*100+c2*10+c3);\nif (bt_,c4=1+rand(9);c5=1+rand(9);c6=1+rand(9),0);\ns=9/max(c4,max(c5,c6));\nq4=int(c4*s*100)+int(c5*s*10)+int(s*c6);\nq2=r5*0.9+0.1;\nbt_=bt;\n\n\nif (bt, reg05=2+int(rand(4)); dir=if(rand(1)>0.5,1,-1);gri=3+rand(4)*rand(4),0);\nang += BPM/60*4*dir*dt;\nq5=gri;\nreg60 = 30/fps;\nreg06 = 0.04*aspecty;\nreg32 = aspecty;\n\nq9 = ang*pi/4;\ndec = if(vol>v_,0.5,dec_m);\nv_= dec*v_+(1-dec)*vol;\nq15=sqrt(v_)*0.8;\nq3 = 4;","pixel_eqs_eel":"rot = 0; warp = 0; dy = -0.00;  dx = -1;\n\nzoom = 1;\nrot = 3.1416*2/3 * 0;","warp":"#define tex sampler_MilkDrop3_003\nsampler tex;\n\nshader_body\n{\n\nvec2 xy1=vec2(0);\nvec2 xymod=uv-.5;\n\nxy1.x=sin(time/3)*xymod.x-0.5-cos(time/3)*xymod.y;\nxy1.y=cos(time/3)*xymod.x-0.5+sin(rad*50)*xymod.y;\n\nuv=xy1*aspect.xy;\n\nret =texture(tex, uv ).xyz;\n\n}","comp":"vec3 ret1;\nvec2 zz, uv0, uv1,uv2,uv3,uv4;\nfloat smask;\n\nfloat aTan2(float y, float x) {float angle;\t float abs_y = abs(y);\nif (x >= 0) {float r = (x - abs_y) / (x + abs_y); angle = 1-r;} \nelse {float r = (x + abs_y) / (abs_y - x); angle = 3-r; }\t\nangle = angle * .25;\nreturn y < 0 ? -angle : angle;}\n\nfloat _pow(float b,float e){return pow(b,e);}\nvec2  _pow(vec2  b,float e){return pow(b,vec2(e));}\nvec3  _pow(vec3  b,float e){return pow(b,vec3(e));}\nvec4  _pow(vec4  b,float e){return pow(b,vec4(e));}\nshader_body { ;\nuv0 = uv;\nuv1 = (uv-.5)*aspect.xy;\n\nuv1 = (uv - .5) * aspect.xy;    \nfloat stars = 0; float dist, inten;\nint n = 1;\nint anz = 4;\nwhile (n <= anz) {\n  dist = (1-fract(1.0/anz*n+.10*time)) * (1-.2*rad);\n  inten =  (1-dist);\n  uv3 = (uv1+vec2(q1,q2));\n   uv4 = 64*dist*uv3;\n  smask = (texture (sampler_pw_noise_lq,uv4/256).xyz).g-.9;\n  stars += max(stars,clamp(inten*(0.11/length(abs(fract(uv4)-0.47))*smask), 0.0, 1.0));\nn++;\n}\nuv2 = uv1 - vec2(q5,q6);\nfloat beat = (mid - 0.45) * (mid > 0.45)*2;\nfloat flash = .01/(length(uv2))*min(3,_pow(beat,1));\nflash *= flash/(abs(fract(3*aTan2(uv2.x,uv2.y)+time*2)-.5));\nret1 = max(texture(sampler_main, uv0).xyz*2,((texture(sampler_blur2, uv0).xyz * scale2) + bias2)*2);\n//ret =clamp(0.022/length(sin(uv3)), 0.0, 1.0)*vec3(0.2,2.6,0.1); //MilkDrop2077 color mod\nret += clamp(_pow(stars,2), 0.0, 1.0);\nret *= clamp(1-2*lum(ret1), 0.0, 1.0);\nret +=  ret1;\nret -= 0.1;\n//ret += 2*clamp(flash, 0.0, 1.0)*vec3(2.2,2.9,0.7); //MilkDrop2077 color mod\nret /= vec3(2.0,2.9,2.3);\nret*=1.4;\n}","warp_hlsl":"#define tex sampler_MilkDrop3_003\nsampler tex;\n\nshader_body\n{\n\nfloat2 xy1=0;\nfloat2 xymod=uv-.5;\n\nxy1.x=sin(time/3)*xymod.x-0.5-cos(time/3)*xymod.y;\nxy1.y=cos(time/3)*xymod.x-0.5+sin(rad*50)*xymod.y;\n\nuv=xy1*aspect.xy;\n\nret = tex2D(tex, uv ).xyz;\n\n}","comp_hlsl":"sampler sampler_pw_noise_lq;\nfloat3 ret1;\nfloat2 zz, uv0, uv1,uv2,uv3,uv4;\nfloat smask;\n\nfloat aTan2(float y, float x) {float angle;\t float abs_y = abs(y);\nif (x >= 0) {float r = (x - abs_y) / (x + abs_y); angle = 1-r;} \nelse {float r = (x + abs_y) / (abs_y - x); angle = 3-r; }\t\nangle = angle * .25;\nreturn y < 0 ? -angle : angle;}\n\nshader_body { ;\nuv0 = uv;\nuv1 = (uv-.5)*aspect.xy;\n\nuv1 = (uv - .5) * aspect.xy;    \nfloat stars = 0; float dist, inten;\nint n = 1;\nint anz = 4;\nwhile (n <= anz) {\n  dist = (1-frac(1.0/anz*n+.10*time)) * (1-.2*rad);\n  inten =  (1-dist);\n  uv3 = (uv1+float2(q1,q2));\n   uv4 = 64*dist*uv3;\n  smask = (tex2D (sampler_pw_noise_lq,uv4/256)).g-.9;\n  stars += max(stars,saturate(inten*(0.11/length(abs(frac(uv4)-0.47))*smask)));\nn++;\n}\nuv2 = uv1 - float2(q5,q6);\nfloat beat = (mid - 0.45) * (mid > 0.45)*2;\nfloat flash = .01/(length(uv2))*min(3,pow(beat,1));\nflash *= flash/(abs(frac(3*aTan2(uv2.x,uv2.y)+time*2)-.5));\nret1 = max(GetPixel(uv0)*2,GetBlur2(uv0)*2);\n//ret = saturate(0.022/length(sin(uv3)))*float3(0.2,2.6,0.1); //MilkDrop2077 color mod\nret += saturate(pow(stars,2));\nret *= saturate(1-2*lum(ret1));\nret +=  ret1;\nret -= 0.1;\n//ret += 2*saturate(flash)*float3(2.2,2.9,0.7); //MilkDrop2077 color mod\nret /= float3(2.0,2.9,2.3);\nret*=1.4;\n}"}