{"baseVals":{"gammaadj":1,"decay":0.995,"echo_zoom":1.007,"echo_orient":3,"additivewave":1,"modwavealphabyvolume":1,"wave_brighten":0,"wrap":0,"wave_a":1.413,"wave_scale":1.131,"wave_smoothing":0,"wave_mystery":-0.66,"modwavealphastart":2,"modwavealphaend":2,"warpanimspeed":0.626,"warpscale":1.331,"fshader":10,"zoom":0.99951,"warp":0.08925,"wave_r":0,"wave_g":0,"wave_x":0.24,"wave_y":0.44,"ob_size":0.5,"ob_r":0.01,"ib_size":0.26,"mv_x":64,"mv_y":48,"mv_l":0,"mv_a":0},"shapes":[{"baseVals":{"enabled":1,"sides":3,"additive":1,"num_inst":41,"rad":0.0277,"ang":6.03186,"tex_ang":6.03186,"tex_zoom":0.6839,"a":0.2,"r2":1,"g2":0,"a2":0.2,"border_r":0,"border_g":0,"border_b":0,"border_a":0.2},"init_eqs_str":"a['t1'] = 0; a['ydir'] = 0; a['q15'] = 0; a['q5'] = 0; a['coff1'] = 0; a['coff2'] = 0; a['volint'] = 0; a['q4'] = 0; a['dir'] = 0; a['bdir'] = 0; a['q16'] = 0; a['negsw2'] = 0; a['t2'] = 0; a['q17'] = 0; a['roll'] = 0; a['negsw1'] = 0; a['q3'] = 0; a['xdir'] = 0; a['isiz'] = 0; a['q30'] = 0; ","frame_eqs_str":"a['x']=a['q3']; a['y']=a['q4']; a['rad']=a['q5']; a['isiz']=a['q30']; a['volint']=Math.floor((((a['bass']+a['treb'])+a['mid'])*2.5)); a['coff1']=((mod(rand(((a['instance']-a['instance'])+10)),a['volint'])+0.01)*0.1); a['coff2']=((mod(rand(((a['instance']-a['instance'])+10)),a['volint'])+0.01)*0.1); a['negsw1']=pow(-1, mod(rand(2),2)); a['negsw2']=pow(-1, mod(rand(2),2)); a['x']=((0.5+((a['isiz']*a['coff1'])*a['negsw1']))+(a['x']-0.5)); a['y']=((0.5+((a['isiz']*a['coff2'])*a['negsw2']))+(a['y']-0.5)); a['xdir']=(a['x']-a['t1']); a['ydir']=(a['y']-a['t2']); a['dir']=div(a['xdir'],a['ydir']); a['bdir']=((0.5*a['bdir'])+(0.5*a['dir'])); a['roll']=(a['roll']-a['bdir']); a['ang']=div(a['roll'],6.28); a['t1']=a['x']; a['t2']=a['y']; a['r']=a['q15']; a['g']=a['q16']; a['b']=a['q17']; a['r2']=a['q16']; a['g2']=a['q15']; a['b2']=a['q17']; a['border_r']=a['q17']; a['border_g']=a['q16']; a['border_b']=a['q15'];"},{"baseVals":{"enabled":1,"additive":1,"num_inst":41,"rad":0.0277,"ang":6.03186,"tex_ang":6.03186,"tex_zoom":0.6839,"r":0,"b":1,"a":0.2,"g2":0,"b2":1,"a2":0.2,"border_r":0,"border_g":0,"border_b":0,"border_a":0.2},"init_eqs_str":"a['t1'] = 0; a['ydir'] = 0; a['q15'] = 0; a['q6'] = 0; a['coff1'] = 0; a['coff2'] = 0; a['volint'] = 0; a['dir'] = 0; a['bdir'] = 0; a['q16'] = 0; a['negsw2'] = 0; a['t2'] = 0; a['q17'] = 0; a['roll'] = 0; a['negsw1'] = 0; a['q7'] = 0; a['xdir'] = 0; a['isiz'] = 0; a['q30'] = 0; a['q8'] = 0; ","frame_eqs_str":"a['x']=a['q6']; a['y']=a['q7']; a['rad']=a['q8']; a['isiz']=a['q30']; a['volint']=Math.floor((((a['bass']+a['treb'])+a['mid'])*2.5)); a['coff1']=((mod(rand(((a['instance']-a['instance'])+10)),a['volint'])+0.01)*0.1); a['coff2']=((mod(rand(((a['instance']-a['instance'])+10)),a['volint'])+0.01)*0.1); a['negsw1']=pow(-1, mod(rand(2),2)); a['negsw2']=pow(-1, mod(rand(2),2)); a['x']=((0.5+((a['isiz']*a['coff1'])*a['negsw1']))+(a['x']-0.5)); a['y']=((0.5+((a['isiz']*a['coff2'])*a['negsw2']))+(a['y']-0.5)); a['xdir']=(a['x']-a['t1']); a['ydir']=(a['y']-a['t2']); a['dir']=div(a['xdir'],a['ydir']); a['bdir']=((0.5*a['bdir'])+(0.5*a['dir'])); a['roll']=(a['roll']-a['bdir']); a['ang']=div(a['roll'],6.28); a['t1']=a['x']; a['t2']=a['y']; a['r']=a['q17']; a['g']=a['q15']; a['b']=a['q16']; a['r2']=a['q16']; a['g2']=a['q17']; a['b2']=a['q15']; a['border_r']=a['q16']; a['border_g']=a['q15']; a['border_b']=a['q17'];"},{"baseVals":{"enabled":1,"sides":5,"additive":1,"num_inst":41,"rad":0.0277,"ang":6.03186,"tex_ang":6.03186,"tex_zoom":0.6839,"r":0,"g":1,"a":0.2,"a2":0.2,"border_r":0,"border_g":0,"border_b":0,"border_a":0.2},"init_eqs_str":"a['t1'] = 0; a['ydir'] = 0; a['q15'] = 0; a['q9'] = 0; a['coff1'] = 0; a['q11'] = 0; a['q10'] = 0; a['coff2'] = 0; a['volint'] = 0; a['dir'] = 0; a['bdir'] = 0; a['q16'] = 0; a['negsw2'] = 0; a['t2'] = 0; a['q17'] = 0; a['roll'] = 0; a['negsw1'] = 0; a['xdir'] = 0; a['isiz'] = 0; a['q30'] = 0; ","frame_eqs_str":"a['x']=a['q9']; a['y']=a['q10']; a['rad']=a['q11']; a['isiz']=a['q30']; a['volint']=Math.floor((((a['bass']+a['treb'])+a['mid'])*2.5)); a['coff1']=((mod(rand(((a['instance']-a['instance'])+10)),a['volint'])+0.01)*0.1); a['coff2']=((mod(rand(((a['instance']-a['instance'])+10)),a['volint'])+0.01)*0.1); a['negsw1']=pow(-1, mod(rand(2),2)); a['negsw2']=pow(-1, mod(rand(2),2)); a['x']=((0.5+((a['isiz']*a['coff1'])*a['negsw1']))+(a['x']-0.5)); a['y']=((0.5+((a['isiz']*a['coff2'])*a['negsw2']))+(a['y']-0.5)); a['xdir']=(a['x']-a['t1']); a['ydir']=(a['y']-a['t2']); a['dir']=div(a['xdir'],a['ydir']); a['bdir']=((0.5*a['bdir'])+(0.5*a['dir'])); a['roll']=(a['roll']-a['bdir']); a['ang']=div(a['roll'],6.28); a['t1']=a['x']; a['t2']=a['y']; a['r']=a['q17']; a['g']=a['q16']; a['b']=a['q15']; a['r2']=a['q16']; a['g2']=a['q17']; a['b2']=a['q15']; a['border_r']=a['q15']; a['border_g']=a['q16']; a['border_b']=a['q17'];"},{"baseVals":{"enabled":1,"sides":7,"additive":1,"thickoutline":1,"num_inst":41,"rad":0.0277,"ang":6.03186,"tex_ang":6.03186,"tex_zoom":0.6839,"r":0,"g":1,"a":0,"border_a":1},"init_eqs_str":"a['q12'] = 0; a['t1'] = 0; a['ydir'] = 0; a['q13'] = 0; a['q15'] = 0; a['coff1'] = 0; a['coff2'] = 0; a['volint'] = 0; a['dir'] = 0; a['bdir'] = 0; a['q16'] = 0; a['negsw2'] = 0; a['t2'] = 0; a['q17'] = 0; a['roll'] = 0; a['negsw1'] = 0; a['q14'] = 0; a['xdir'] = 0; a['isiz'] = 0; a['q30'] = 0; ","frame_eqs_str":"a['x']=a['q12']; a['y']=a['q13']; a['rad']=a['q14']; a['isiz']=a['q30']; a['volint']=Math.floor((((a['bass']+a['treb'])+a['mid'])*2.5)); a['coff1']=((mod(rand(((a['instance']-a['instance'])+10)),a['volint'])+0.01)*0.1); a['coff2']=((mod(rand(((a['instance']-a['instance'])+10)),a['volint'])+0.01)*0.1); a['negsw1']=pow(-1, mod(rand(2),2)); a['negsw2']=pow(-1, mod(rand(2),2)); a['x']=((0.5+((a['isiz']*a['coff1'])*a['negsw1']))+(a['x']-0.5)); a['y']=((0.5+((a['isiz']*a['coff2'])*a['negsw2']))+(a['y']-0.5)); a['xdir']=(a['x']-a['t1']); a['ydir']=(a['y']-a['t2']); a['dir']=div(a['xdir'],a['ydir']); a['bdir']=((0.5*a['bdir'])+(0.5*a['dir'])); a['roll']=(a['roll']+a['bdir']); a['ang']=div(a['roll'],6.28); a['t1']=a['x']; a['t2']=a['y']; a['border_r']=a['q15']; a['border_g']=a['q17']; a['border_b']=a['q16'];"}],"waves":[{"baseVals":{"sep":256,"spectrum":1,"thick":1,"smoothing":0,"enabled":0},"init_eqs_str":"a['sw'] = 0; a['mo'] = 0; a['q15'] = 0; a['osa'] = 0; a['q31'] = 0; a['q10'] = 0; a['q16'] = 0; a['mod'] = 0; a['q17'] = 0; a['q32'] = 0; ","frame_eqs_str":"","point_eqs_str":"a['sw']=((1-a['sw'])*above(a['sample'], 0)); a['osa']=(a['sample']*above(a['sample'], 0)); a['mod']=((pow((a['value1']*2), 2)*sign(a['value1']))*0.5); a['mod']=a['value1']; a['mod']=(a['mod']*a['sw']); a['y']=((Math.abs(a['sw'])>0.00001)?(a['osa']):(a['sample'])); a['y']=a['sample']; a['x']=(0.5-(a['mod']*0.5)); a['osa']=a['sample']; a['mo']=((3.7+(a['mod']*6))+a['q10']); a['r']=a['q16']; a['g']=a['q17']; a['b']=a['q15']; a['a']=(1-(Math.abs(a['mod'])*12)); a['a']=(1-a['sw']); a['a']=Math.max(0, Math.min(a['a'], 1)); a['x']=(((a['x']-0.5)*div(a['q31'],a['q32']))+0.5); a['y']=(((a['y']-0.5)*div(a['q32'],a['q31']))+0.5);"},{"baseVals":{"sep":256,"spectrum":1,"thick":1,"smoothing":0,"enabled":0},"init_eqs_str":"a['sw'] = 0; a['mo'] = 0; a['q15'] = 0; a['osa'] = 0; a['q31'] = 0; a['q10'] = 0; a['q16'] = 0; a['mod'] = 0; a['q17'] = 0; a['q32'] = 0; ","frame_eqs_str":"","point_eqs_str":"a['sw']=((1-a['sw'])*below(a['sample'], 1)); a['osa']=(a['sample']*above(a['sample'], 0)); a['mod']=((pow((a['value2']*2), 2)*sign(a['value2']))*0.5); a['mod']=a['value2']; a['mod']=(a['mod']*a['sw']); a['y']=((Math.abs(a['sw'])>0.00001)?(a['osa']):(a['sample'])); a['y']=a['sample']; a['x']=(0.5+(a['mod']*0.5)); a['osa']=a['sample']; a['mo']=((3.7+(a['mod']*6))+a['q10']); a['r']=a['q17']; a['g']=a['q15']; a['b']=a['q16']; a['a']=(1-(Math.abs(a['mod'])*12)); a['a']=(1-a['sw']); a['a']=Math.max(0, Math.min(a['a'], 1)); a['x']=(((a['x']-0.5)*div(a['q31'],a['q32']))+0.5); a['y']=(((a['y']-0.5)*div(a['q32'],a['q31']))+0.5);"},{"baseVals":{"spectrum":1,"g":0,"b":0,"enabled":0},"init_eqs_str":"a['w'] = 0; a['t5'] = 0; a['ref_w'] = 0; a['t1'] = 0; a['q15'] = 0; a['q9'] = 0; a['x'] = 0; a['t8'] = 0; a['v'] = 0; a['t3'] = 0; a['q10'] = 0; a['q16'] = 0; a['y'] = 0; a['q19'] = 0; a['t2'] = 0; a['t4'] = 0; a['q20'] = 0; a['chance']=0;","frame_eqs_str":"a['x']=((Math.abs(a['q9'])>0.00001)?(a['q15']):(a['x'])); a['y']=((Math.abs(a['q9'])>0.00001)?(a['q16']):(a['y'])); a['v']=((Math.abs(a['q9'])>0.00001)?(a['q19']):(a['v'])); a['w']=((Math.abs(a['q9'])>0.00001)?(a['q20']):(a['w'])); a['ref_w']=((Math.abs(a['q9'])>0.00001)?(a['q10']):(a['ref_w'])); a['t1']=a['x']; a['t2']=a['y']; a['t3']=a['v']; a['t4']=a['w']; a['t5']=a['ref_w']; a['t8']=1;","point_eqs_str":"a['x']=(a['t1']+((((a['sample']*Math.sin(a['t5']))*a['t3'])*20)*Math.cos((a['t4']-a['t5'])))); a['y']=(a['t2']+((((a['sample']*Math.cos(a['t5']))*a['t3'])*20)*Math.cos((a['t4']-a['t5'])))); a['x']=(0.5+(a['x']-0.5)); a['y']=(0.5+(a['y']-0.5));"},{"baseVals":{"spectrum":1,"g":0,"b":0,"enabled":0},"init_eqs_str":"a['w'] = 0; a['t5'] = 0; a['ref_w'] = 0; a['t1'] = 0; a['q15'] = 0; a['q9'] = 0; a['x'] = 0; a['t8'] = 0; a['v'] = 0; a['t3'] = 0; a['q10'] = 0; a['q16'] = 0; a['y'] = 0; a['q19'] = 0; a['t2'] = 0; a['t4'] = 0; a['q20'] = 0; a['chance']=0;","frame_eqs_str":"a['x']=((Math.abs(a['q9'])>0.00001)?(a['q15']):(a['x'])); a['y']=((Math.abs(a['q9'])>0.00001)?(a['q16']):(a['y'])); a['v']=((Math.abs(a['q9'])>0.00001)?(a['q19']):(a['v'])); a['w']=((Math.abs(a['q9'])>0.00001)?(a['q20']):(a['w'])); a['ref_w']=((Math.abs(a['q9'])>0.00001)?((a['q10']+Math.asin(1))):(a['ref_w'])); a['t1']=a['x']; a['t2']=a['y']; a['t3']=a['v']; a['t4']=a['w']; a['t5']=a['ref_w']; a['t8']=1;","point_eqs_str":"a['x']=(a['t1']+((((a['sample']*Math.sin(a['t5']))*a['t3'])*20)*Math.cos((a['t4']-a['t5'])))); a['y']=(a['t2']+((((a['sample']*Math.cos(a['t5']))*a['t3'])*20)*Math.cos((a['t4']-a['t5'])))); a['x']=(0.5+(a['x']-0.5)); a['y']=(0.5+(a['y']-0.5));"}],"init_eqs_str":"a['y3'] = 0; a['y1'] = 0; a['q12'] = 0; a['w2'] = 0; a['ref_ang'] = 0; a['x1'] = 0; a['vx3'] = 0; a['q13'] = 0; a['q15'] = 0; a['q6'] = 0; a['q1'] = 0; a['q5'] = 0; a['q9'] = 0; a['vx1'] = 0; a['vx4'] = 0; a['x3'] = 0; a['q31'] = 0; a['q11'] = 0; a['q10'] = 0; a['q4'] = 0; a['vy4'] = 0; a['bounce'] = 0; a['q16'] = 0; a['x4'] = 0; a['w1'] = 0; a['r'] = 0; a['x2'] = 0; a['q19'] = 0; a['q17'] = 0; a['vy2'] = 0; a['y2'] = 0; a['vy1'] = 0; a['q2'] = 0; a['q14'] = 0; a['v1'] = 0; a['vx2'] = 0; a['q3'] = 0; a['q32'] = 0; a['y4'] = 0; a['q7'] = 0; a['vy3'] = 0; a['q30'] = 0; a['v2'] = 0; a['q20'] = 0; a['q8'] = 0; a['x1']=0.5; a['x2']=0.51; a['y2']=0.9; a['y1']=0.7; a['x3']=0.8; a['y3']=0.5; a['x4']=0.2; a['y4']=0.5; a['ax1']=0; a['ay1']=0; a['ax2']=0; a['ay2']=0; a['ax3']=0; a['ay3']=0; a['vx1']=0.000; a['vx2']=0.000;","frame_eqs_str":"a['zoom']=1; a['warp']=0; a['wave_a']=0; a['r']=(0.04+(Math.max(a['bass_att'], a['treb_att'])*0.04)); a['bounce']=below(a['y1'], a['r']); a['y1']=(a['y1']+a['vy1']); a['vy1']=((Math.abs(a['bounce'])>0.00001)?(((Math.abs(a['vy1'])*0.94)+((a['r']-a['y1'])*0.1))):((a['vy1']-div((0.0003*60),a['fps'])))); a['bounce']=below(a['x1'], a['r']); a['x1']=(a['x1']+a['vx1']); a['vx1']=((Math.abs(a['bounce'])>0.00001)?(((Math.abs(a['vx1'])*0.94)+((a['r']-a['x1'])*0.1))):(a['vx1'])); a['bounce']=above(a['x1'], (1-a['r'])); a['vx1']=((Math.abs(a['bounce'])>0.00001)?(((-Math.abs(a['vx1'])*0.94)+(((1-a['r'])-a['x1'])*0.04))):(a['vx1'])); a['bounce']=above(a['y1'], (1-a['r'])); a['vy1']=((Math.abs(a['bounce'])>0.00001)?(((-Math.abs(a['vy1'])*0.94)+(((1-a['r'])-a['y1'])*0.04))):(a['vy1'])); a['bounce']=below(a['y2'], a['r']); a['y2']=(a['y2']+a['vy2']); a['vy2']=((Math.abs(a['bounce'])>0.00001)?(((Math.abs(a['vy2'])*0.94)+((a['r']-a['y2'])*0.1))):((a['vy2']-div((0.0003*60),a['fps'])))); a['bounce']=below(a['x2'], a['r']); a['x2']=(a['x2']+a['vx2']); a['vx2']=((Math.abs(a['bounce'])>0.00001)?(((Math.abs(a['vx2'])*0.94)+((a['r']-a['x2'])*0.1))):(a['vx2'])); a['bounce']=above(a['x2'], (1-a['r'])); a['vx2']=((Math.abs(a['bounce'])>0.00001)?(((-Math.abs(a['vx2'])*0.94)+(((1-a['r'])-a['x2'])*0.1))):(a['vx2'])); a['bounce']=above(a['y2'], (1-a['r'])); a['vy2']=((Math.abs(a['bounce'])>0.00001)?(((-Math.abs(a['vy2'])*0.94)+(((1-a['r'])-a['y2'])*0.1))):(a['vy2'])); a['bounce']=below(a['y3'], a['r']); a['y3']=(a['y3']+a['vy3']); a['vy3']=((Math.abs(a['bounce'])>0.00001)?(((Math.abs(a['vy3'])*0.94)+((a['r']-a['y3'])*0.1))):((a['vy3']-div((0.0003*60),a['fps'])))); a['bounce']=below(a['x3'], a['r']); a['x3']=(a['x3']+a['vx3']); a['vx3']=((Math.abs(a['bounce'])>0.00001)?(((Math.abs(a['vx3'])*0.94)+((a['r']-a['x3'])*0.1))):(a['vx3'])); a['bounce']=above(a['x3'], (1-a['r'])); a['vx3']=((Math.abs(a['bounce'])>0.00001)?(((-Math.abs(a['vx3'])*0.94)+(((1-a['r'])-a['x3'])*0.1))):(a['vx3'])); a['bounce']=above(a['y3'], (1-a['r'])); a['vy3']=((Math.abs(a['bounce'])>0.00001)?(((-Math.abs(a['vy3'])*0.94)+(((1-a['r'])-a['y3'])*0.1))):(a['vy3'])); a['bounce']=below(a['y4'], a['r']); a['y4']=(a['y4']+a['vy4']); a['vy4']=((Math.abs(a['bounce'])>0.00001)?(((Math.abs(a['vy4'])*0.94)+((a['r']-a['y4'])*0.1))):((a['vy4']-div((0.0003*60),a['fps'])))); a['bounce']=below(a['x4'], a['r']); a['x4']=(a['x4']+a['vx4']); a['vx4']=((Math.abs(a['bounce'])>0.00001)?(((Math.abs(a['vx4'])*0.94)+((a['r']-a['x4'])*0.1))):(a['vx4'])); a['bounce']=above(a['x4'], (1-a['r'])); a['vx4']=((Math.abs(a['bounce'])>0.00001)?(((-Math.abs(a['vx4'])*0.94)+(((1-a['r'])-a['x4'])*0.1))):(a['vx4'])); a['bounce']=above(a['y4'], (1-a['r'])); a['vy4']=((Math.abs(a['bounce'])>0.00001)?(((-Math.abs(a['vy4'])*0.94)+(((1-a['r'])-a['y4'])*0.1))):(a['vy4'])); a['bounce']=below(sqrt((sqr((((a['x1']+a['vx1'])-a['x2'])-a['vx2']))+sqr((((a['y1']+a['vy1'])-a['y2'])-a['vy2'])))), (2*a['r'])); a['ref_ang']=(Math.atan2((a['x2']-a['x1']), (a['y2']-a['y1']))+Math.asin(1)); a['v1']=sqrt(((a['vx1']*a['vx1'])+(a['vy1']*a['vy1']))); a['v2']=sqrt(((a['vx2']*a['vx2'])+(a['vy2']*a['vy2']))); a['w1']=Math.atan2(a['vx1'], a['vy1']); a['w2']=Math.atan2(a['vx2'], a['vy2']); a['vx1']=((Math.abs(a['bounce'])>0.00001)?((((Math.sin(a['ref_ang'])*a['v1'])*Math.cos((a['w1']-a['ref_ang'])))+((Math.sin((a['ref_ang']+Math.asin(1)))*a['v2'])*Math.cos(((a['w2']-a['ref_ang'])-Math.asin(1)))))):(a['vx1'])); a['vy1']=((Math.abs(a['bounce'])>0.00001)?((((Math.cos(a['ref_ang'])*a['v1'])*Math.cos((a['w1']-a['ref_ang'])))+((Math.cos((a['ref_ang']+Math.asin(1)))*a['v2'])*Math.cos(((a['w2']-a['ref_ang'])-Math.asin(1)))))):(a['vy1'])); a['vx2']=((Math.abs(a['bounce'])>0.00001)?((((Math.sin(a['ref_ang'])*a['v2'])*Math.cos((a['w2']-a['ref_ang'])))+((Math.sin((a['ref_ang']+Math.asin(1)))*a['v1'])*Math.cos(((a['w1']-a['ref_ang'])-Math.asin(1)))))):(a['vx2'])); a['vy2']=((Math.abs(a['bounce'])>0.00001)?((((Math.cos(a['ref_ang'])*a['v2'])*Math.cos((a['w2']-a['ref_ang'])))+((Math.cos((a['ref_ang']+Math.asin(1)))*a['v1'])*Math.cos(((a['w1']-a['ref_ang'])-Math.asin(1)))))):(a['vy2'])); a['bounce']=below(sqrt((sqr((((a['x1']+a['vx1'])-a['x3'])-a['vx3']))+sqr((((a['y1']+a['vy1'])-a['y3'])-a['vy3'])))), (2*a['r'])); a['ref_ang']=(Math.atan2((a['x3']-a['x1']), (a['y3']-a['y1']))+Math.asin(1)); a['v1']=sqrt(((a['vx1']*a['vx1'])+(a['vy1']*a['vy1']))); a['v2']=sqrt(((a['vx3']*a['vx3'])+(a['vy3']*a['vy3']))); a['w1']=Math.atan2(a['vx1'], a['vy1']); a['w2']=Math.atan2(a['vx3'], a['vy3']); a['vx1']=((Math.abs(a['bounce'])>0.00001)?((((Math.sin(a['ref_ang'])*a['v1'])*Math.cos((a['w1']-a['ref_ang'])))+((Math.sin((a['ref_ang']+Math.asin(1)))*a['v2'])*Math.cos(((a['w2']-a['ref_ang'])-Math.asin(1)))))):(a['vx1'])); a['vy1']=((Math.abs(a['bounce'])>0.00001)?((((Math.cos(a['ref_ang'])*a['v1'])*Math.cos((a['w1']-a['ref_ang'])))+((Math.cos((a['ref_ang']+Math.asin(1)))*a['v2'])*Math.cos(((a['w2']-a['ref_ang'])-Math.asin(1)))))):(a['vy1'])); a['vx3']=((Math.abs(a['bounce'])>0.00001)?((((Math.sin(a['ref_ang'])*a['v2'])*Math.cos((a['w2']-a['ref_ang'])))+((Math.sin((a['ref_ang']+Math.asin(1)))*a['v1'])*Math.cos(((a['w1']-a['ref_ang'])-Math.asin(1)))))):(a['vx3'])); a['vy3']=((Math.abs(a['bounce'])>0.00001)?((((Math.cos(a['ref_ang'])*a['v2'])*Math.cos((a['w2']-a['ref_ang'])))+((Math.cos((a['ref_ang']+Math.asin(1)))*a['v1'])*Math.cos(((a['w1']-a['ref_ang'])-Math.asin(1)))))):(a['vy3'])); a['bounce']=below(sqrt((sqr((((a['x2']+a['vx2'])-a['x3'])-a['vx3']))+sqr((((a['y2']+a['vy2'])-a['y3'])-a['vy3'])))), (2*a['r'])); a['ref_ang']=(Math.atan2((a['x3']-a['x2']), (a['y3']-a['y2']))+Math.asin(1)); a['v1']=sqrt(((a['vx2']*a['vx2'])+(a['vy2']*a['vy2']))); a['v2']=sqrt(((a['vx3']*a['vx3'])+(a['vy3']*a['vy3']))); a['w1']=Math.atan2(a['vx2'], a['vy2']); a['w2']=Math.atan2(a['vx3'], a['vy3']); a['vx2']=((Math.abs(a['bounce'])>0.00001)?((((Math.sin(a['ref_ang'])*a['v1'])*Math.cos((a['w1']-a['ref_ang'])))+((Math.sin((a['ref_ang']+Math.asin(1)))*a['v2'])*Math.cos(((a['w2']-a['ref_ang'])-Math.asin(1)))))):(a['vx2'])); a['vy2']=((Math.abs(a['bounce'])>0.00001)?((((Math.cos(a['ref_ang'])*a['v1'])*Math.cos((a['w1']-a['ref_ang'])))+((Math.cos((a['ref_ang']+Math.asin(1)))*a['v2'])*Math.cos(((a['w2']-a['ref_ang'])-Math.asin(1)))))):(a['vy2'])); a['vx3']=((Math.abs(a['bounce'])>0.00001)?((((Math.sin(a['ref_ang'])*a['v2'])*Math.cos((a['w2']-a['ref_ang'])))+((Math.sin((a['ref_ang']+Math.asin(1)))*a['v1'])*Math.cos(((a['w1']-a['ref_ang'])-Math.asin(1)))))):(a['vx3'])); a['vy3']=((Math.abs(a['bounce'])>0.00001)?((((Math.cos(a['ref_ang'])*a['v2'])*Math.cos((a['w2']-a['ref_ang'])))+((Math.cos((a['ref_ang']+Math.asin(1)))*a['v1'])*Math.cos(((a['w1']-a['ref_ang'])-Math.asin(1)))))):(a['vy3'])); a['bounce']=below(sqrt((sqr((((a['x1']+a['vx1'])-a['x4'])-a['vx4']))+sqr((((a['y1']+a['vy1'])-a['y4'])-a['vy4'])))), (2*a['r'])); a['ref_ang']=(Math.atan2((a['x4']-a['x1']), (a['y4']-a['y1']))+Math.asin(1)); a['v1']=sqrt(((a['vx1']*a['vx1'])+(a['vy1']*a['vy1']))); a['v2']=sqrt(((a['vx4']*a['vx4'])+(a['vy4']*a['vy4']))); a['w1']=Math.atan2(a['vx1'], a['vy1']); a['w2']=Math.atan2(a['vx4'], a['vy4']); a['vx1']=((Math.abs(a['bounce'])>0.00001)?((((Math.sin(a['ref_ang'])*a['v1'])*Math.cos((a['w1']-a['ref_ang'])))+((Math.sin((a['ref_ang']+Math.asin(1)))*a['v2'])*Math.cos(((a['w2']-a['ref_ang'])-Math.asin(1)))))):(a['vx1'])); a['vy1']=((Math.abs(a['bounce'])>0.00001)?((((Math.cos(a['ref_ang'])*a['v1'])*Math.cos((a['w1']-a['ref_ang'])))+((Math.cos((a['ref_ang']+Math.asin(1)))*a['v2'])*Math.cos(((a['w2']-a['ref_ang'])-Math.asin(1)))))):(a['vy1'])); a['vx4']=((Math.abs(a['bounce'])>0.00001)?((((Math.sin(a['ref_ang'])*a['v2'])*Math.cos((a['w2']-a['ref_ang'])))+((Math.sin((a['ref_ang']+Math.asin(1)))*a['v1'])*Math.cos(((a['w1']-a['ref_ang'])-Math.asin(1)))))):(a['vx4'])); a['vy4']=((Math.abs(a['bounce'])>0.00001)?((((Math.cos(a['ref_ang'])*a['v2'])*Math.cos((a['w2']-a['ref_ang'])))+((Math.cos((a['ref_ang']+Math.asin(1)))*a['v1'])*Math.cos(((a['w1']-a['ref_ang'])-Math.asin(1)))))):(a['vy4'])); a['bounce']=below(sqrt((sqr((((a['x2']+a['vx2'])-a['x4'])-a['vx4']))+sqr((((a['y2']+a['vy2'])-a['y4'])-a['vy4'])))), (2*a['r'])); a['ref_ang']=(Math.atan2((a['x4']-a['x2']), (a['y4']-a['y2']))+Math.asin(1)); a['v1']=sqrt(((a['vx2']*a['vx2'])+(a['vy2']*a['vy2']))); a['v2']=sqrt(((a['vx4']*a['vx4'])+(a['vy4']*a['vy4']))); a['w1']=Math.atan2(a['vx2'], a['vy2']); a['w2']=Math.atan2(a['vx4'], a['vy4']); a['vx2']=((Math.abs(a['bounce'])>0.00001)?((((Math.sin(a['ref_ang'])*a['v1'])*Math.cos((a['w1']-a['ref_ang'])))+((Math.sin((a['ref_ang']+Math.asin(1)))*a['v2'])*Math.cos(((a['w2']-a['ref_ang'])-Math.asin(1)))))):(a['vx2'])); a['vy2']=((Math.abs(a['bounce'])>0.00001)?((((Math.cos(a['ref_ang'])*a['v1'])*Math.cos((a['w1']-a['ref_ang'])))+((Math.cos((a['ref_ang']+Math.asin(1)))*a['v2'])*Math.cos(((a['w2']-a['ref_ang'])-Math.asin(1)))))):(a['vy2'])); a['vx4']=((Math.abs(a['bounce'])>0.00001)?((((Math.sin(a['ref_ang'])*a['v2'])*Math.cos((a['w2']-a['ref_ang'])))+((Math.sin((a['ref_ang']+Math.asin(1)))*a['v1'])*Math.cos(((a['w1']-a['ref_ang'])-Math.asin(1)))))):(a['vx4'])); a['vy4']=((Math.abs(a['bounce'])>0.00001)?((((Math.cos(a['ref_ang'])*a['v2'])*Math.cos((a['w2']-a['ref_ang'])))+((Math.cos((a['ref_ang']+Math.asin(1)))*a['v1'])*Math.cos(((a['w1']-a['ref_ang'])-Math.asin(1)))))):(a['vy4'])); a['bounce']=below(sqrt((sqr((((a['x3']+a['vx3'])-a['x4'])-a['vx4']))+sqr((((a['y3']+a['vy3'])-a['y4'])-a['vy4'])))), (2*a['r'])); a['ref_ang']=(Math.atan2((a['x4']-a['x3']), (a['y4']-a['y3']))+Math.asin(1)); a['v1']=sqrt(((a['vx3']*a['vx3'])+(a['vy3']*a['vy3']))); a['v2']=sqrt(((a['vx4']*a['vx4'])+(a['vy4']*a['vy4']))); a['w1']=Math.atan2(a['vx3'], a['vy3']); a['w2']=Math.atan2(a['vx4'], a['vy4']); a['vx3']=((Math.abs(a['bounce'])>0.00001)?((((Math.sin(a['ref_ang'])*a['v1'])*Math.cos((a['w1']-a['ref_ang'])))+((Math.sin((a['ref_ang']+Math.asin(1)))*a['v2'])*Math.cos(((a['w2']-a['ref_ang'])-Math.asin(1)))))):(a['vx3'])); a['vy3']=((Math.abs(a['bounce'])>0.00001)?((((Math.cos(a['ref_ang'])*a['v1'])*Math.cos((a['w1']-a['ref_ang'])))+((Math.cos((a['ref_ang']+Math.asin(1)))*a['v2'])*Math.cos(((a['w2']-a['ref_ang'])-Math.asin(1)))))):(a['vy3'])); a['vx4']=((Math.abs(a['bounce'])>0.00001)?((((Math.sin(a['ref_ang'])*a['v2'])*Math.cos((a['w2']-a['ref_ang'])))+((Math.sin((a['ref_ang']+Math.asin(1)))*a['v1'])*Math.cos(((a['w1']-a['ref_ang'])-Math.asin(1)))))):(a['vx4'])); a['vy4']=((Math.abs(a['bounce'])>0.00001)?((((Math.cos(a['ref_ang'])*a['v2'])*Math.cos((a['w2']-a['ref_ang'])))+((Math.cos((a['ref_ang']+Math.asin(1)))*a['v1'])*Math.cos(((a['w1']-a['ref_ang'])-Math.asin(1)))))):(a['vy4'])); a['q1']=a['aspectx']; a['q2']=a['aspecty']; a['q3']=a['x1']; a['q4']=a['y1']; a['q5']=(a['r']*2); a['q6']=a['x2']; a['q7']=a['y2']; a['q8']=(a['r']*2); a['q9']=a['x3']; a['q10']=a['y3']; a['q11']=(a['r']*2); a['q12']=a['x4']; a['q13']=a['y4']; a['q14']=(a['r']*2); a['q30']=0.2; a['q20']=((4*Math.asin(-1))*0.33333333333333); a['q15']=((Math.sin((((((a['time']+a['bass'])+a['treb'])+a['mid'])*0.4)-(0*a['q20'])))+1)*0.5); a['q16']=((Math.sin((((((a['time']+a['bass'])+a['treb'])+a['mid'])*0.4)-(1*a['q20'])))+1)*0.5); a['q17']=((Math.sin((((((a['time']+a['bass'])+a['treb'])+a['mid'])*0.4)-(2*a['q20'])))+1)*0.5); a['monitor']=a['q19']; a['q31']=a['pixelsx']; a['q32']=a['pixelsy'];","pixel_eqs_str":"","warp":"shader_body\n{\nvec2 _uv = uv;\n\n\n//_uv = uv_orig;\nfloat corr = (texsize.xy*texsize_noise_lq.zw).x;\nvec2 uv1 = vec2(_uv.x-0.5,_uv.y-0.5)*aspect.xy;\n\nvec2 tmp = uv1;\ntmp.x = ang*3.0;\ntmp.y = rad;\nuv1 = tmp;\n\nvec3 noise = (texture(sampler_noise_lq,corr*_uv/2.0+q23).xyz+1.0);\n\nvec3 ret1 = ((texture(sampler_blur1, _uv).xyz * scale1) + bias1)-.3;\nvec3 crisp = vec3(vec3(texture(sampler_main, _uv+ret1.xy*.01 ).xy + noise.xy*0.1, 0.0));\nvec3 blur = ((texture(sampler_blur1, _uv/4.0+.4*vec2(.3*ret1.x,ret1.y)).xyz * scale1) + bias1) - noise*.1;\n\nret = -.4*blur + crisp;\n    \n ret *= 0.98 * pow(1.0-.01*q28*q28*rad,2.0); \n  ret -= 0.04;\n\n\n\n\n\n\n}","comp":"shader_body\n{\n//uv1 is rect. screen, center at (0.0;0)\nvec2 uv1 = vec2((uv-0.5));// * aspect.xy;\n\nvec2 hor = vec2 (.002,0.0);\nvec2 ver = vec2 (0.0,.002);\n\nfloat f0 = .7;\nfloat dx = (f0*(texture(sampler_main,uv+hor).xyz  - texture(sampler_main,uv-hor).xyz)).x;\nfloat dy = (f0*(texture(sampler_main,uv+ver).xyz  - texture(sampler_main,uv-ver).xyz)).x;\n\nvec2 dz = vec2 (dx,dy);\ndz -= ((texture(sampler_main, uv).xyz)).x;\n\nvec2 rs1 = (mat2(_qb) * 16.0*uv1)+time/8.0;\n\nvec3 canv1 = texture(sampler_main, (uv-.5)*.95+.5).xyz;\n\nfloat scale = 100.0;\nrs1 = rs1 + dz*scale*.2;\n\nfloat lava = texture (sampler_noise_hq,rs1/scale).x;\nlava = clamp(-q9*abs (lava) + 1.0, 0.0, 1.0);\nvec3 lay1 = clamp(vec3 (lava,lava*(lava-0.55)*2.0,(lava-1.0)*16.0), 0.0, 1.0);\n\nret = .6*(canv1-.05)*vec3 (q15,q16,q17)  + lay1;\n\n\n\n}"}